hkqr/__init__.py
hkqr/specs.json
hkqr-0.1.0.dist-info/METADATA
hkqr-0.1.0.dist-info/WHEEL
hkqr-0.1.0.dist-info/licenses/LICENSE
hkqr-0.1.0.dist-info/RECORD
