Metadata-Version: 2.1
Name: hkqr
Version: 0.1.0
Summary: Hong Kong HKQR FPS Code generation for Python
Project-URL: Homepage, https://github.com/pulsely/hkqr
Project-URL: Bug Tracker, https://github.com/pulsely/hkqr/issues
Author-email: Pulsely <python@pulsely.com>
License-File: LICENSE
Classifier: License :: OSI Approved :: GNU General Public License (GPL)
Classifier: Operating System :: OS Independent
Classifier: Programming Language :: Python :: 3
Requires-Python: >=3.8
